nwae/utils/BaseConfig.py
nwae/utils/Cleanup.py
nwae/utils/CmdLine.py
nwae/utils/Datetime.py
nwae/utils/EmailAlerts.py
nwae/utils/Encode.py
nwae/utils/FileUtils.py
nwae/utils/Hash.py
nwae/utils/Json.py
nwae/utils/LockFile.py
nwae/utils/Log.py
nwae/utils/ObjectPersistence.py
nwae/utils/Profiling.py
nwae/utils/Rest.py
nwae/utils/SendMail.py
nwae/utils/SignalHandler.py
nwae/utils/StringUtils.py
nwae/utils/ThreadGroup.py
nwae/utils/UnitTest.py
nwae/utils/audio/AudioUtils.py
nwae/utils/data/BaseDataCache.py
nwae/utils/data/DataPreprcscr.py
nwae/utils/dataencoder/OneHotEncoder.py
nwae/utils/networking/Ssl.py
nwae/utils/networking/WebSocketClient.py
nwae/utils/sec/AccessToken.py
nwae/utils/sec/Encrypt.py
nwae/utils/sec/OauthClient.py
nwae/utils/sec/Totp.py
nwae.utils-1.8.5.dist-info/METADATA
nwae.utils-1.8.5.dist-info/WHEEL
nwae.utils-1.8.5.dist-info/top_level.txt
nwae.utils-1.8.5.dist-info/RECORD
