Metadata-Version: 2.1
Name: nwae.utils
Version: 1.8.5
Summary: Basic & Useful Utilities
Home-page: UNKNOWN
Author: nwae
Author-email: mapktah@ya.ru
License: UNKNOWN
Platform: UNKNOWN
